ans_env_loader/__init__.py
ans_env_loader/version.py
ans_env_loader-0.20250728.1.dist-info/METADATA
ans_env_loader-0.20250728.1.dist-info/WHEEL
ans_env_loader-0.20250728.1.dist-info/RECORD
