Metadata-Version: 2.4
Name: ans-env-loader
Version: 0.20250728.1
Author-email: Randy Syring <randy.syring@level12.io>
Requires-Python: ~=3.12.0
Requires-Dist: ansible-core>=2.18.6
